bimdp/__init__.py
bimdp/biclassifier.py
bimdp/biflow.py
bimdp/binode.py
bimdp/hinet/__init__.py
bimdp/hinet/biflownode.py
bimdp/hinet/bihtmlvisitor.py
bimdp/hinet/bilayer.py
bimdp/hinet/biswitchboard.py
bimdp/inspection/__init__.py
bimdp/inspection/facade.py
bimdp/inspection/slideshow.py
bimdp/inspection/tracer.py
bimdp/inspection/utils.py
bimdp/nodes/__init__.py
bimdp/nodes/autogen.py
bimdp/nodes/gradient.py
bimdp/nodes/miscnodes.py
bimdp/parallel/__init__.py
bimdp/parallel/parallelbiflow.py
bimdp/parallel/parallelbihinet.py
bimdp/test/__init__.py
bimdp/test/_tools.py
bimdp/test/conftest.py
bimdp/test/ide_run.py
bimdp/test/test_biflow.py
bimdp/test/test_bihinet.py
bimdp/test/test_binode.py
bimdp/test/test_gradient.py
bimdp/test/test_namespace_fixups.py
bimdp/test/test_parallelbiflow.py
bimdp/test/test_parallelbihinet.py
mdp/__init__.py
mdp/classifier_node.py
mdp/configuration.py
mdp/extension.py
mdp/helper_funcs.py
mdp/linear_flows.py
mdp/linear_flows_online.py
mdp/repo_revision.py
mdp/signal_node.py
mdp/signal_node_online.py
mdp/caching/__init__.py
mdp/caching/caching_extension.py
mdp/graph/__init__.py
mdp/graph/graph.py
mdp/hinet/__init__.py
mdp/hinet/flownode.py
mdp/hinet/flownode_online.py
mdp/hinet/hinet.css
mdp/hinet/htmlvisitor.py
mdp/hinet/layer.py
mdp/hinet/layer_online.py
mdp/hinet/switchboard.py
mdp/hinet/switchboard_factory.py
mdp/nodes/__init__.py
mdp/nodes/classifier_nodes.py
mdp/nodes/convolution_nodes.py
mdp/nodes/em_nodes.py
mdp/nodes/expansion_nodes.py
mdp/nodes/fda_nodes.py
mdp/nodes/gsfa_nodes.py
mdp/nodes/ica_nodes.py
mdp/nodes/isfa_nodes.py
mdp/nodes/jade.py
mdp/nodes/libsvm_classifier.py
mdp/nodes/lle_nodes.py
mdp/nodes/mca_nodes_online.py
mdp/nodes/misc_nodes.py
mdp/nodes/neural_gas_nodes.py
mdp/nodes/nipals.py
mdp/nodes/pca_nodes.py
mdp/nodes/pca_nodes_online.py
mdp/nodes/rbm_nodes.py
mdp/nodes/recursive_expansion_nodes.py
mdp/nodes/regression_nodes.py
mdp/nodes/scikits_nodes.py
mdp/nodes/sfa_nodes.py
mdp/nodes/sfa_nodes_online.py
MDP-3.6.dist-info/METADATA
MDP-3.6.dist-info/WHEEL
MDP-3.6.dist-info/top_level.txt
MDP-3.6.dist-info/RECORD
