Metadata-Version: 2.1
Name: MDP
Version: 3.6
Summary: MDP is a Python library for building complex data processing software by combining widely used machine learning algorithms into pipelines and networks.
Home-page: https://mdpdocs.readthedocs.io
Author: MDP Developers
Author-email: mdp-toolkit@python.org
Maintainer: MDP Developers
Maintainer-email: mdp-toolkit@python.org
License: https://raw.githubusercontent.com/mdp-toolkit/mdp-toolkit/master/COPYRIGHT
Download-URL: https://github.com/mdp-toolkit/mdp-toolkit/archive/MDP-3.6.zip
Platform: Any
Classifier: Development Status :: 5 - Production/Stable
Classifier: Intended Audience :: Developers
Classifier: Intended Audience :: Education
Classifier: Intended Audience :: Science/Research
Classifier: License :: OSI Approved :: BSD License
Classifier: Operating System :: OS Independent
Classifier: Programming Language :: Python
Classifier: Programming Language :: Python :: 2
Classifier: Programming Language :: Python :: 3
Classifier: Topic :: Scientific/Engineering :: Information Analysis
Classifier: Topic :: Scientific/Engineering :: Mathematics
Requires-Dist: numpy
Requires-Dist: future
Provides-Extra: joblib
Requires-Dist: joblib ; extra == 'joblib'
Provides-Extra: libsvm
Requires-Dist: libsvm ; extra == 'libsvm'
Provides-Extra: pp
Requires-Dist: pp ; extra == 'pp'
Provides-Extra: pytest
Requires-Dist: pytest ; extra == 'pytest'
Provides-Extra: scikit-learn
Requires-Dist: scikit-learn ; extra == 'scikit-learn'
Provides-Extra: scipy
Requires-Dist: scipy ; extra == 'scipy'
